MANIFEST.in
README.rst
setup.py
pingtop/__init__.py
pingtop/ping.py
pingtop.egg-info/PKG-INFO
pingtop.egg-info/SOURCES.txt
pingtop.egg-info/dependency_links.txt
pingtop.egg-info/entry_points.txt
pingtop.egg-info/requires.txt
pingtop.egg-info/top_level.txt