Metadata-Version: 2.1
Name: pingtop
Version: 0.3.0
Summary: Ping multiple servers and show the result in a top like terminal UI.
Home-page: https://github.com/laixintao/pingtop
Author: laixintao
Author-email: laixintaoo@gmail.com
License: UNKNOWN
Keywords: IP,ping,icmp
Platform: UNKNOWN
Classifier: Programming Language :: Python
Classifier: Programming Language :: Python :: 3.7
Classifier: Intended Audience :: Developers
Classifier: License :: OSI Approved :: MIT License
Classifier: Operating System :: OS Independent
